video_info_mcp/__init__.py
video_info_mcp/main.py
mcpcn_video_info_mcp-0.1.2.dist-info/METADATA
mcpcn_video_info_mcp-0.1.2.dist-info/WHEEL
mcpcn_video_info_mcp-0.1.2.dist-info/entry_points.txt
mcpcn_video_info_mcp-0.1.2.dist-info/RECORD
